numpy_io/.gitignore
numpy_io/README.MD
numpy_io/__init__.py
numpy_io/core/__init__.py
numpy_io/core/numpyadapter.py
numpy_io/core/parallel.py
numpy_io/core/reader.py
numpy_io/core/writer.py
numpy_io/examples/README.md
numpy_io/examples/__init__.py
numpy_io/examples/auto_parallel_writer.py
numpy_io/examples/auto_writer.py
numpy_io/examples/demo_arrow_writer.py
numpy_io/examples/demo_arrow_writer2.py
numpy_io/examples/demo_parquet_writer.py
numpy_io/examples/leveldb_readwriter_example.py
numpy_io/examples/lmdb_readwriter_example.py
numpy_io/examples/memory_raw_readwriter_example.py
numpy_io/examples/memory_readwriter_example.py
numpy_io/examples/record_numpywriter_example.py
numpy_io/examples/record_reader_example.py
numpy_io/examples/record_shuffle_example.py
numpy_io/examples/record_writer_example.py
numpy_io/examples/testing/__init__.py
numpy_io/examples/testing/demo_arrow_writer.py
numpy_io/examples/testing/demo_arrow_writer2.py
numpy_io/examples/testing/demo_parquet_writer.py
numpy_io/examples/testing/lmdb_test.py
numpy_io/examples/testing/test_mem.py
numpy_io/examples/testing/test_mutiprocess.py
numpy_io/pytorch_loader/__init__.py
numpy_io/pytorch_loader/data_helper.py
numpy_io/pytorch_loader/dataloaders.py
numpy_io/pytorch_loader/tokenizer_config_helper.py
numpy_io-0.0.10.dist-info/METADATA
numpy_io-0.0.10.dist-info/WHEEL
numpy_io-0.0.10.dist-info/top_level.txt
numpy_io-0.0.10.dist-info/RECORD
